AUTHORS
LICENSE
MANIFEST.in
README.rst
setup.py
django_template_mail.egg-info/PKG-INFO
django_template_mail.egg-info/SOURCES.txt
django_template_mail.egg-info/dependency_links.txt
django_template_mail.egg-info/top_level.txt
templatemail/__init__.py
templatemail/backends/__init__.py
templatemail/backends/base.py
templatemail/backends/console.py
templatemail/backends/dummy.py
templatemail/backends/filebased.py
templatemail/backends/locmem.py
templatemail/backends/smtp.py