Metadata-Version: 1.0
Name: django-template-mail
Version: 0.1
Summary: A Django application to send email using django's templating system
Home-page: http://github.com/benoitbar/django-template-mail/
Author: Benoît Bar
Author-email: bar.benoit@gmail.com
License: MIT
Platform: any
Classifier: Development Status :: 4 - Beta
Classifier: Intended Audience :: Developers
Classifier: License :: OSI Approved :: MIT License
Classifier: Operating System :: OS Independent
Classifier: Programming Language :: Python
Classifier: Topic :: Software Development :: Libraries :: Python Modules
Classifier: Framework :: Django
